pulsar_producer/__init__.py
pulsar_producer/cli.py
pulsar_producer/producer.py
pulsar_producer-0.1.0.dist-info/entry_points.txt
pulsar_producer-0.1.0.dist-info/WHEEL
pulsar_producer-0.1.0.dist-info/METADATA
pulsar_producer-0.1.0.dist-info/RECORD
