Metadata-Version: 2.1
Name: pulsar-producer
Version: 0.1.0
Summary: CLI that help developers to publish messages into any pulsar topic in order to test features (usually, consumers) that relies on a pulsar consumer
Home-page: https://github.com/vandaimer/pulsar-producer
License: MIT
Keywords: apache-pulsar,producer,python
Author: Luiz Filipe
Author-email: you@example.com
Requires-Python: >=3.8,<4.0
Classifier: License :: OSI Approved :: MIT License
Classifier: Programming Language :: Python :: 3
Classifier: Programming Language :: Python :: 3.8
Classifier: Programming Language :: Python :: 3.9
Classifier: Programming Language :: Python :: 3.10
Classifier: Programming Language :: Python :: 3.11
Requires-Dist: pulsar-client (>=2.10.2,<3.0.0)
Requires-Dist: typer (>=0.7.0,<0.8.0)
Project-URL: Repository, https://github.com/vandaimer/pulsar-producer
